<annotation>
	<folder>ResizedAugmentedImages</folder>
	<filename>Invoice_86_affine.jpg</filename>
	<path>D:\annotations\ResizedAugmentedImages\Invoice_86_affine.jpg</path>
	<source>
		<database>Unknown</database>
	</source>
	<size>
		<width>640</width>
		<height>640</height>
		<depth>3</depth>
	</size>
	<segmented>0</segmented>
	<object>
		<name>CompanyName</name>
		<pose>Unspecified</pose>
		<truncated>0</truncated>
		<difficult>0</difficult>
		<bndbox>
			<xmin>139</xmin>
			<ymin>161</ymin>
			<xmax>225</xmax>
			<ymax>175</ymax>
		</bndbox>
	</object>
	<object>
		<name>CompanyAddress</name>
		<pose>Unspecified</pose>
		<truncated>0</truncated>
		<difficult>0</difficult>
		<bndbox>
			<xmin>258</xmin>
			<ymin>140</ymin>
			<xmax>321</xmax>
			<ymax>166</ymax>
		</bndbox>
	</object>
	<object>
		<name>CustomerAddress</name>
		<pose>Unspecified</pose>
		<truncated>0</truncated>
		<difficult>0</difficult>
		<bndbox>
			<xmin>147</xmin>
			<ymin>204</ymin>
			<xmax>217</xmax>
			<ymax>230</ymax>
		</bndbox>
	</object>
	<object>
		<name>Total</name>
		<pose>Unspecified</pose>
		<truncated>0</truncated>
		<difficult>0</difficult>
		<bndbox>
			<xmin>399</xmin>
			<ymin>198</ymin>
			<xmax>441</xmax>
			<ymax>221</ymax>
		</bndbox>
	</object>
</annotation>
